openVO/__init__.py
openVO/stereo_camera.py
openVO/stereo_odometer.py
openVO/utils/__init__.py
openVO/utils/drawPoseOnImage.py
openVO/utils/rot2RPY.py
openVO-0.0.6.dist-info/LICENSE
openVO-0.0.6.dist-info/METADATA
openVO-0.0.6.dist-info/WHEEL
openVO-0.0.6.dist-info/top_level.txt
openVO-0.0.6.dist-info/RECORD
